{
  "complete": true,
  "list": [
    {
      "id": 1,
      "_id": "abc",
      "listHeader": "https://avatars1.githubusercontent.com/u/3006580?v=3&s=40",
      "title": "这就是你扩散到付款这就是你扩散到付款这就是你扩散到付款这就是你扩散到付款,这就是你扩散到付款,这就是你扩散到付款,这就是你扩散到付款,",
      "iconStar": "fa-star-o",
      "content": {
        "姓名": 1,
        "电话": 222
      }
    },
    {
      "id": 2,
      "_id": "def",
      "listHeader": "https://avatars1.githubusercontent.com/u/3006580?v=3&s=40",
      "title": "titleTest1,titleTest1titleTest1titleTest1",
      "iconStar": "fa-star-o",
      "content": {
        "姓名": 1,
        "电话": 222
      }
    }
  ]
}